jupyter_syncthing_proxy/__init__.py
jupyter_syncthing_proxy/icons/logo.svg
jupyter_syncthing_proxy-1.0.3.dist-info/LICENSE
jupyter_syncthing_proxy-1.0.3.dist-info/METADATA
jupyter_syncthing_proxy-1.0.3.dist-info/WHEEL
jupyter_syncthing_proxy-1.0.3.dist-info/entry_points.txt
jupyter_syncthing_proxy-1.0.3.dist-info/top_level.txt
jupyter_syncthing_proxy-1.0.3.dist-info/RECORD
