Metadata-Version: 2.1
Name: jupyter-syncthing-proxy
Version: 1.0.3
Summary: yuvipanda@gmail.com
Home-page: https://github.com/yuvipanda/jupyter-syncthing-proxy
Author: Yuvi Panda
License: UNKNOWN
Keywords: Jupyter
Platform: UNKNOWN
Classifier: Framework :: Jupyter
License-File: LICENSE
Requires-Dist: jupyter-server-proxy
